nep29/__init__.py
nep29/_static_version.py
nep29/_version.py
nep29/nep29.py
nep29/tests/__init__.py
nep29/tests/test_nep29.py
nep29-0.0.17.dist-info/LICENSE
nep29-0.0.17.dist-info/METADATA
nep29-0.0.17.dist-info/WHEEL
nep29-0.0.17.dist-info/entry_points.txt
nep29-0.0.17.dist-info/top_level.txt
nep29-0.0.17.dist-info/RECORD
