Metadata-Version: 2.1
Name: nep29
Version: 0.0.17
Summary: NEP29 Calculator tools
Home-page: https://github.com/hmaarrfk/nep29
Author: Mark Harfouche
Author-email: mark.harfouche@gmail.com
License: BSD license
Keywords: nep29
Classifier: Development Status :: 2 - Pre-Alpha
Classifier: Intended Audience :: Developers
Classifier: License :: OSI Approved :: BSD License
Classifier: Natural Language :: English
Classifier: Programming Language :: Python :: 3
Classifier: Programming Language :: Python :: 3.6
Classifier: Programming Language :: Python :: 3.7
Classifier: Programming Language :: Python :: 3.8
Classifier: Programming Language :: Python :: 3.9
Requires-Python: >=3.6
License-File: LICENSE
Requires-Dist: requests
Requires-Dist: prettytable
Requires-Dist: packaging
